molingtool_async/__init__.py
molingtool_async/mcp/again_client_session.py
molingtool_async/mcp/client.py
molingtool_async-1.0.2.dist-info/METADATA
molingtool_async-1.0.2.dist-info/WHEEL
molingtool_async-1.0.2.dist-info/top_level.txt
molingtool_async-1.0.2.dist-info/RECORD
