Metadata-Version: 2.1
Name: molingtool-async
Version: 1.0.2
Summary: 工业化! yyds
Home-page: https://www.python.org
Author: mengling
Author-email: 1321443305@qq.com
Requires-Python: >3.6
Provides-Extra: all
Requires-Dist: mcp ; extra == 'all'
Requires-Dist: openai ; extra == 'all'
Provides-Extra: mcp
Requires-Dist: mcp ; extra == 'mcp'
Requires-Dist: openai ; extra == 'mcp'
